[{"id":1,"name":"Artkma","position":"active","workPlace":"WAREHOUSE","active":true},{"id":2,"name":"Test Employee","position":"Manager","workPlace":null,"active":true},{"id":3,"name":"Test Employee","position":"Manager","workPlace":null,"active":true},{"id":4,"name":"Test Employee","position":"Manager","workPlace":null,"active":true},{"id":5,"name":"Test Employee","position":"Manager","workPlace":null,"active":false},{"id":6,"name":"Updated Employee","position":"Senior Manager","workPlace":null,"active":true},{"id":7,"name":"Test Employee","position":"Manager","workPlace":null,"active":true},{"id":8,"name":"Test Employee 1","position":"Manager","workPlace":null,"active":true},{"id":9,"name":"Test Employee 2","position":"Developer","workPlace":null,"active":true},{"id":10,"name":"Test Employee 1","position":"Manager","workPlace":null,"active":true},{"id":11,"name":"Test Employee 2","position":"Developer","workPlace":null,"active":false},{"id":12,"name":"Test Employee","position":"Manager","workPlace":null,"active":true},{"id":13,"name":"Test Employee","position":"Manager","workPlace":null,"active":true},{"id":14,"name":"Test Employee","position":"Manager","workPlace":null,"active":true},{"id":15,"name":"Test Employee","position":"Manager","workPlace":null,"active":false},{"id":16,"name":"Updated Employee","position":"Senior Manager","workPlace":null,"active":true},{"id":17,"name":"Test Employee","position":"Manager","workPlace":null,"active":true},{"id":18,"name":"Test Employee 1","position":"Manager","workPlace":null,"active":true},{"id":19,"name":"Test Employee 2","position":"Developer","workPlace":null,"active":true},{"id":20,"name":"Test Employee 1","position":"Manager","workPlace":null,"active":true},{"id":21,"name":"Test Employee 2","position":"Developer","workPlace":null,"active":false},{"id":22,"name":"Test Employee","position":"Manager","workPlace":null,"active":true},{"id":23,"name":"Test Employee","position":"Manager","workPlace":null,"active":true},{"id":24,"name":"Test Employee","position":"Manager","workPlace":null,"active":true},{"id":25,"name":"Test Employee","position":"Manager","workPlace":null,"active":false},{"id":26,"name":"Updated Employee","position":"Senior Manager","workPlace":null,"active":true},{"id":27,"name":"Test Employee","position":"Manager","workPlace":null,"active":true},{"id":28,"name":"Test Employee 1","position":"Manager","workPlace":null,"active":true},{"id":29,"name":"Test Employee 2","position":"Developer","workPlace":null,"active":true},{"id":30,"name":"Test Employee 1","position":"Manager","workPlace":null,"active":true},{"id":31,"name":"Test Employee 2","position":"Developer","workPlace":null,"active":false},{"id":32,"name":"Test Employee","position":"Manager","workPlace":null,"active":true},{"id":33,"name":"Test Employee","position":"Manager","workPlace":null,"active":true},{"id":34,"name":"Test Employee","position":"Manager","workPlace":null,"active":true},{"id":35,"name":"Test Employee","position":"Manager","workPlace":null,"active":false},{"id":36,"name":"Updated Employee","position":"Senior Manager","workPlace":null,"active":true},{"id":37,"name":"Test Employee","position":"Manager","workPlace":null,"active":true},{"id":38,"name":"Test Employee 1","position":"Manager","workPlace":null,"active":true},{"id":39,"name":"Test Employee 2","position":"Developer","workPlace":null,"active":true},{"id":40,"name":"Test Employee 1","position":"Manager","workPlace":null,"active":true},{"id":41,"name":"Test Employee 2","position":"Developer","workPlace":null,"active":false},{"id":42,"name":"Test Employee","position":"Manager","workPlace":null,"active":true},{"id":43,"name":"Test Employee","position":"Manager","workPlace":null,"active":true},{"id":44,"name":"Test Employee","position":"Manager","workPlace":null,"active":true},{"id":45,"name":"Test Employee","position":"Manager","workPlace":null,"active":false},{"id":46,"name":"Updated Employee","position":"Senior Manager","workPlace":null,"active":true},{"id":47,"name":"Test Employee","position":"Manager","workPlace":null,"active":true},{"id":48,"name":"Test Employee 1","position":"Manager","workPlace":null,"active":true},{"id":49,"name":"Test Employee 2","position":"Developer","workPlace":null,"active":true},{"id":50,"name":"Test Employee 1","position":"Manager","workPlace":null,"active":true},{"id":51,"name":"Test Employee 2","position":"Developer","workPlace":null,"active":false},{"id":52,"name":"Test Employee","position":"Manager","workPlace":null,"active":true},{"id":53,"name":"Test Employee","position":"Manager","workPlace":null,"active":true},{"id":54,"name":"Test Employee","position":"Manager","workPlace":null,"active":true},{"id":55,"name":"Test Employee","position":"Manager","workPlace":null,"active":false},{"id":56,"name":"Updated Employee","position":"Senior Manager","workPlace":null,"active":true},{"id":57,"name":"Test Employee","position":"Manager","workPlace":null,"active":true},{"id":58,"name":"Test Employee 1","position":"Manager","workPlace":null,"active":true},{"id":59,"name":"Test Employee 2","position":"Developer","workPlace":null,"active":true},{"id":60,"name":"Test Employee 1","position":"Manager","workPlace":null,"active":true},{"id":61,"name":"Test Employee 2","position":"Developer","workPlace":null,"active":false},{"id":62,"name":"Test Employee","position":"Manager","workPlace":null,"active":true},{"id":63,"name":"Test Employee","position":"Manager","workPlace":null,"active":true},{"id":64,"name":"Test Employee","position":"Manager","workPlace":null,"active":true},{"id":65,"name":"Test Employee","position":"Manager","workPlace":null,"active":false},{"id":66,"name":"Updated Employee","position":"Senior Manager","workPlace":null,"active":true},{"id":67,"name":"Test Employee","position":"Manager","workPlace":null,"active":true},{"id":68,"name":"Test Employee 1","position":"Manager","workPlace":null,"active":true},{"id":69,"name":"Test Employee 2","position":"Developer","workPlace":null,"active":true},{"id":70,"name":"Test Employee 1","position":"Manager","workPlace":null,"active":true},{"id":71,"name":"Test Employee 2","position":"Developer","workPlace":null,"active":false}]